LICENSE
MANIFEST.in
NOTICE
README.md
setup.cfg
setup.py
CommandCenter/__init__.py
CommandCenter/api_client.py
CommandCenter/configuration.py
CommandCenter/rest.py
CommandCenter/setup.py
CommandCenter/api/__init__.py
CommandCenter/api/access_logs_api.py
CommandCenter/api/cloud_settings_api.py
CommandCenter/api/cloud_users_api.py
CommandCenter/api/clouds_api.py
CommandCenter/api/comments_api.py
CommandCenter/api/computes_api.py
CommandCenter/api/custom_networks_api.py
CommandCenter/api/drive_api.py
CommandCenter/api/drive_types_api.py
CommandCenter/api/engine_types_api.py
CommandCenter/api/fault_domains_api.py
CommandCenter/api/images_api.py
CommandCenter/api/logs_api.py
CommandCenter/api/remote_authentications_api.py
CommandCenter/api/roles_api.py
CommandCenter/api/software_install_api.py
CommandCenter/api/storage_nodes_api.py
CommandCenter/api/users_api.py
CommandCenter/api/vlan_api.py
CommandCenter/api/volume_api.py
CommandCenter/api/vpsa_object_storage_api.py
CommandCenter/api/vpsa_storage_array_api.py
CommandCenter/models/__init__.py
CommandCenter/models/add_address_to_remote_rsyslog_server_list.py
CommandCenter/models/add_cloud_control_ip_whitelisting_entries.py
CommandCenter/models/add_drives.py
CommandCenter/models/add_drives_to_zios.py
CommandCenter/models/add_ip_range_to_custom_net.py
CommandCenter/models/add_node.py
CommandCenter/models/add_provisioned_vlan_or_range.py
CommandCenter/models/add_proxy_virtual_controller_zios.py
CommandCenter/models/add_virtual_nets_to_zios.py
CommandCenter/models/add_virtual_network_interface.py
CommandCenter/models/add_vpsa_endpoints_conf_for_upload_types.py
CommandCenter/models/add_zios_endpoints_configs_for_upload_types.py
CommandCenter/models/allocate_vlan.py
CommandCenter/models/allocate_vlan_to_cloud_user.py
CommandCenter/models/app_engine_type.py
CommandCenter/models/assign_public_ip.py
CommandCenter/models/assign_public_ip_zios.py
CommandCenter/models/change_cache.py
CommandCenter/models/change_engine_type_zios.py
zadarapyV2.egg-info/PKG-INFO
zadarapyV2.egg-info/SOURCES.txt
zadarapyV2.egg-info/dependency_links.txt
zadarapyV2.egg-info/not-zip-safe
zadarapyV2.egg-info/requires.txt
zadarapyV2.egg-info/top_level.txt