Metadata-Version: 2.1
Name: zadarapyV2
Version: 23.9.2.274
Summary: zadara api
Home-page: https://github.com/zadarastorage/zadara-clients/tree/master/zadarapyV2
Author-email: harel.feldman@zadarastorage.com
Keywords: zadarapy
License-File: LICENSE
